ABOUT.rst
API.md
AUTHORS
CHANGELOG.docx
ChangeLog
DEVELOP.md
LICENSE
README.md
README_ZH.md
dev-requirements.txt
log.txt
requirements.txt
screenshot.jpg
setup.cfg
setup.py
.github/workflows/publish-to-pypi.yml
.vscode/settings.json
mtat_weditor.egg-info/PKG-INFO
mtat_weditor.egg-info/SOURCES.txt
mtat_weditor.egg-info/dependency_links.txt
mtat_weditor.egg-info/entry_points.txt
mtat_weditor.egg-info/not-zip-safe
mtat_weditor.egg-info/pbr.json
mtat_weditor.egg-info/requires.txt
mtat_weditor.egg-info/top_level.txt
samples/bg.jpg
samples/bower.json
samples/index.html
samples/ace/ace.js
samples/ace/ext-language_tools.js
samples/ace/keybinding-vim.js
samples/ace/mode-python.js
samples/ace/theme-monokai.js
tests/test_proto.py
tests/test_web_utils.py
weditor/__init__.py
weditor/__main__.py
weditor/page.xml
weditor/static/favicon.ico
weditor/static/loading.svg
weditor/static/running.svg
weditor/static/style.css
weditor/static/ace/ace.js
weditor/static/ace/ext-language_tools.js
weditor/static/ace/keybinding-vim.js
weditor/static/ace/mode-python.js
weditor/static/ace/theme-monokai.js
weditor/static/cdn_libraries/cdn.jsdelivr.net/bootstrap.select/1.12.2/css/bootstrap-select.min.css
weditor/static/cdn_libraries/cdn.jsdelivr.net/bootstrap.select/1.12.2/js/bootstrap-select.js.map
weditor/static/cdn_libraries/cdn.jsdelivr.net/bootstrap.select/1.12.2/js/bootstrap-select.min.js
weditor/static/cdn_libraries/cdn.jsdelivr.net/bootstrap/3.3.7/css/bootstrap.min.css
weditor/static/cdn_libraries/cdn.jsdelivr.net/bootstrap/3.3.7/css/bootstrap.min.css.map
weditor/static/cdn_libraries/cdn.jsdelivr.net/bootstrap/3.3.7/fonts/glyphicons-halflings-regular.woff2
weditor/static/cdn_libraries/cdn.jsdelivr.net/bootstrap/3.3.7/js/bootstrap.min.js
weditor/static/cdn_libraries/cdn.jsdelivr.net/npm/vue-resource@1.5.1
weditor/static/cdn_libraries/cdn.jsdelivr.net/npm/ace-builds@1.4.12/src-noconflict/ace.min.js
weditor/static/cdn_libraries/cdn.jsdelivr.net/npm/ace-builds@1.4.12/src-noconflict/ext-language_tools.min.js
weditor/static/cdn_libraries/cdn.jsdelivr.net/npm/ace-builds@1.4.12/src-noconflict/ext-searchbox.min.js
weditor/static/cdn_libraries/cdn.jsdelivr.net/npm/ace-builds@1.4.12/src-noconflict/mode-python.min.js
