Metadata-Version: 2.1
Name: mtat-weditor
Version: 0.1.2
Summary: tool for writing atx script
Home-page: https://github.com/openatx/weditor
Author: codeskyblue
Author-email: codeskyblue@gmail.com
License: MIT
Classifier: Environment :: Console
Classifier: Intended Audience :: Developers
Classifier: Operating System :: OS Independent
Classifier: Programming Language :: Python
Requires-Python: >=3.6
License-File: LICENSE
